kyqlos/__init__.py
kyqlos/monitor.py
kyqlos/utils.py
kyqlos-0.0.0a1.dist-info/METADATA
kyqlos-0.0.0a1.dist-info/WHEEL
kyqlos-0.0.0a1.dist-info/top_level.txt
kyqlos-0.0.0a1.dist-info/RECORD
