Metadata-Version: 2.1
Name: kyqlos
Version: 0.0.0a1
Summary: A python client package for using the Kyqlos API.
Home-page: UNKNOWN
Author: GRID INC.
Author-email: kyqlos-dev@gridpredict.jp
License: MIT
Keywords: kyqlos
Platform: UNKNOWN
Classifier: License :: OSI Approved :: MIT License
Classifier: Programming Language :: Python :: 3.6
Requires-Dist: dill
Requires-Dist: numpy
Requires-Dist: requests (==2.2.0)
